README.rst
setup.py
md2docx/VERSION
md2docx/__init__.py
md2docx/journal.py
md2docx/main.py
md2docx/prepare_bib.py
md2docx/prepare_docx.py
md2docx/prepare_md.py
md2docx/utils.py
md2docx.egg-info/PKG-INFO
md2docx.egg-info/SOURCES.txt
md2docx.egg-info/dependency_links.txt
md2docx.egg-info/entry_points.txt
md2docx.egg-info/requires.txt
md2docx.egg-info/top_level.txt
md2docx/var/acronyms.txt
md2docx/var/csl
md2docx/var/docx
md2docx/var/docx/reference.docx
md2docx/var/journals/CerebCortex.json
md2docx/var/journals/HumBrainMapp.json
md2docx/var/journals/JNeurosci.json
md2docx/var/journals/Neuroimage.json
md2docx/var/journals/Neuron.json
md2docx/var/nodejs/citeproc.js
md2docx/var/nodejs/processcite.js