Metadata-Version: 1.1
Name: md2docx
Version: 2.0.0
Summary: Use MarkDown to write articles in the correct format
Home-page: http://www.gpiantoni.com/md2docx
Author: Gio Piantoni
Author-email: md2docx@gpiantoni.com
License: GPLv3
Keywords: writing docx markdown journals
Platform: UNKNOWN
Classifier: Development Status :: 4 - Beta
Classifier: Topic :: Scientific/Engineering :: Visualization
Classifier: License :: OSI Approved :: GNU General Public License v3 (GPLv3)
Classifier: Programming Language :: Python :: 3 :: Only
Classifier: Programming Language :: Python :: 3.5
